YangzhongyiYipanQimenShizhan/README.md
YangzhongyiYipanQimenShizhan/__init__.py
YangzhongyiYipanQimenShizhan/__main__.py
YangzhongyiYipanQimenShizhan/file.pdf
YangzhongyiYipanQimenShizhan/index.html
yangzhongyi_yipan_qimen_shizhan-2022.10.22.0.dist-info/METADATA
yangzhongyi_yipan_qimen_shizhan-2022.10.22.0.dist-info/WHEEL
yangzhongyi_yipan_qimen_shizhan-2022.10.22.0.dist-info/entry_points.txt
yangzhongyi_yipan_qimen_shizhan-2022.10.22.0.dist-info/top_level.txt
yangzhongyi_yipan_qimen_shizhan-2022.10.22.0.dist-info/RECORD
